.gitignore
LICENSE
README.md
pyproject.toml
src/feast_gridgain/__init__.py
src/feast_gridgain/base_online_store.py
src/feast_gridgain/gridgain_online_store.py
src/feast_gridgain/ignite_online_store.py
src/feast_gridgain.egg-info/PKG-INFO
src/feast_gridgain.egg-info/SOURCES.txt
src/feast_gridgain.egg-info/dependency_links.txt
src/feast_gridgain.egg-info/requires.txt
src/feast_gridgain.egg-info/top_level.txt
tests/README_TESTS.md
tests/__init__.py
tests/integration/__init__.py
tests/integration/base_test_online_store.py
tests/integration/test_gridgain_online_store.py
tests/integration/test_ignite_online_store.py
tests/unit/__init__.py
tests/unit/base_test_online_store.py
tests/unit/test_gridgain_online_store.py
tests/unit/test_ignite_online_store.py