Metadata-Version: 2.2
Name: feast-gridgain
Version: 1.0.0
Summary: This package makes it possible to use Ignite as online store for Feast.
Author-email: Manini Puranik <manini.puranik@gridgain.com>, Aditi Sharma <aditi.sharma@gridgain.com>
Requires-Python: >=3.11.7
License-File: LICENSE
Requires-Dist: feast==0.38.0
Requires-Dist: pandas==2.2.2
Requires-Dist: numpy==1.26.4
Requires-Dist: pydantic==2.7.4
Requires-Dist: pyignite==0.6.1
Requires-Dist: pygridgain==1.4.0
Provides-Extra: test
Requires-Dist: pytest; extra == "test"
Requires-Dist: pytest-asyncio; extra == "test"
Provides-Extra: coverage
Requires-Dist: pytest-cov; extra == "coverage"
